spdlqj/__init__.py
spdlqj/module.py
spdlqj-0.1.2.dist-info/LICENSE
spdlqj-0.1.2.dist-info/METADATA
spdlqj-0.1.2.dist-info/WHEEL
spdlqj-0.1.2.dist-info/top_level.txt
spdlqj-0.1.2.dist-info/RECORD
