Metadata-Version: 2.1
Name: spdlqj
Version: 0.1.2
Summary: 🇰🇷 Naver Cafe Archive Module
Home-page: https://github.com/kitae0522/Naver-Cafe-Archive
Author: Ted Song
Author-email: kitae040522@gmail.com
License: MIT
License-File: LICENSE
Requires-Dist: setuptools
Requires-Dist: requests
Requires-Dist: pandas
